investlib/__init__.py
investlib/data.py
investlib/filters.py
investlib/rebalance.py
investlib/strategy.py
investlib/utils.py
investlib/report/__init__.py
investlib/report/draw.py
investlib/report/templates/report.html
investlib-0.0.6.dist-info/METADATA
investlib-0.0.6.dist-info/WHEEL
investlib-0.0.6.dist-info/licenses/LICENSE
investlib-0.0.6.dist-info/RECORD
