Metadata-Version: 2.1
Name: investlib
Version: 0.0.6
Summary: InvestLib is a Python package for backtesting ETF investments
Project-URL: Homepage, https://github.com/cellarosi/investlib
Project-URL: Bug Tracker, https://github.com/cellarosi/investlib/issues
Author-email: Cellarosi Marco <cellarosi@gmail.com>
License-File: LICENSE
Classifier: License :: OSI Approved :: GNU General Public License v3 (GPLv3)
Classifier: Operating System :: OS Independent
Classifier: Programming Language :: Python :: 3
Requires-Python: >=3.8
Requires-Dist: certifi==2023.5.7
Requires-Dist: charset-normalizer==3.1.0
Requires-Dist: freezegun==1.2.2
Requires-Dist: idna==3.4
Requires-Dist: numpy==1.24.4
Requires-Dist: pandas==2.0.3
Requires-Dist: plotly==5.15.0
Requires-Dist: python-dateutil==2.8.2
Requires-Dist: pytz==2023.3
Requires-Dist: requests==2.31.0
Requires-Dist: six==1.16.0
Requires-Dist: tzdata==2023.3
Requires-Dist: urllib3==2.0.3
